taperable_helix/__init__.py
taperable_helix/helix.py
taperable_helix-0.8.17.dist-info/AUTHORS.rst
taperable_helix-0.8.17.dist-info/LICENSE
taperable_helix-0.8.17.dist-info/METADATA
taperable_helix-0.8.17.dist-info/WHEEL
taperable_helix-0.8.17.dist-info/top_level.txt
taperable_helix-0.8.17.dist-info/RECORD
