Metadata-Version: 2.1
Name: taperable-helix
Version: 0.8.17
Summary: Generate helixes that can optionally taper to a point at each end.
Home-page: https://github.com/winksaville/py-taperable-helix
Author: Wink Saville
Author-email: wink@saville.com
License: MIT license
Keywords: taperable_helix
Platform: any
Classifier: Development Status :: 2 - Pre-Alpha
Classifier: Intended Audience :: Developers
Classifier: License :: OSI Approved :: MIT License
Classifier: Natural Language :: English
Classifier: Programming Language :: Python :: 3.7
Classifier: Programming Language :: Python :: 3.8
Requires-Python: >=3.7
